chainlit/copilot/dist/assets/logo_dark-COK1dHdN.svg
chainlit/copilot/dist/assets/logo_light-BEEPztD0.svg
chainlit/copilot/dist/index.js
chainlit/frontend/dist/assets/DailyMotion-DRmnB_KO.js
chainlit/frontend/dist/assets/DailyMotion-DRmnB_KO.js.map
chainlit/frontend/dist/assets/Dataframe-CwoSBjxH.js
chainlit/frontend/dist/assets/Dataframe-CwoSBjxH.js.map
chainlit/frontend/dist/assets/Facebook-3Ry2PzWD.js
chainlit/frontend/dist/assets/Facebook-3Ry2PzWD.js.map
chainlit/frontend/dist/assets/FilePlayer-7otRDf4t.js
chainlit/frontend/dist/assets/FilePlayer-7otRDf4t.js.map
chainlit/frontend/dist/assets/index-BIhgNEQJ.css
chainlit/frontend/dist/assets/index-DHWpTT_H.js
chainlit/frontend/dist/assets/index-DHWpTT_H.js.map
chainlit/frontend/dist/assets/Kaltura-CYXQ3TgY.js
chainlit/frontend/dist/assets/Kaltura-CYXQ3TgY.js.map
chainlit/frontend/dist/assets/logo_dark-COK1dHdN.svg
chainlit/frontend/dist/assets/logo_light-BEEPztD0.svg
chainlit/frontend/dist/assets/Mixcloud-v_VCl6Tk.js
chainlit/frontend/dist/assets/Mixcloud-v_VCl6Tk.js.map
chainlit/frontend/dist/assets/Mux-CVDVCnuG.js
chainlit/frontend/dist/assets/Mux-CVDVCnuG.js.map
chainlit/frontend/dist/assets/Preview-B6nQiOKr.js
chainlit/frontend/dist/assets/Preview-B6nQiOKr.js.map
chainlit/frontend/dist/assets/react-plotly-s970RizX.js
chainlit/frontend/dist/assets/react-plotly-s970RizX.js.map
chainlit/frontend/dist/assets/SoundCloud-DskFDhAG.js
chainlit/frontend/dist/assets/SoundCloud-DskFDhAG.js.map
chainlit/frontend/dist/assets/Streamable-2e_BhEYx.js
chainlit/frontend/dist/assets/Streamable-2e_BhEYx.js.map
chainlit/frontend/dist/assets/Twitch-CKa6LLgN.js
chainlit/frontend/dist/assets/Twitch-CKa6LLgN.js.map
chainlit/frontend/dist/assets/Vidyard-Bmk7awRz.js
chainlit/frontend/dist/assets/Vidyard-Bmk7awRz.js.map
chainlit/frontend/dist/assets/Vimeo-Ck7JaOI0.js
chainlit/frontend/dist/assets/Vimeo-Ck7JaOI0.js.map
chainlit/frontend/dist/assets/Wistia-Be3Dcr5v.js
chainlit/frontend/dist/assets/Wistia-Be3Dcr5v.js.map
chainlit_mardonio-2.6.0.dist-info/entry_points.txt
chainlit_mardonio-2.6.0.dist-info/METADATA
chainlit_mardonio-2.6.0.dist-info/WHEEL
chainlit_mardonio-2.6.0.dist-info/RECORD
